{
  "id": 487,
  "name": "giratina-altered",
  "genus": "Renegade Pokémon",
  "types": [
    "ghost",
    "dragon"
  ],
  "abilities": [
    {
      "name": "pressure",
      "hidden": false
    },
    {
      "name": "telepathy",
      "hidden": true
    }
  ],
  "moves": [
    "cut",
    "fly",
    "headbutt",
    "body-slam",
    "take-down",
    "roar",
    "hyper-beam",
    "strength",
    "thunderbolt",
    "thunder-wave",
    "thunder",
    "earthquake",
    "toxic",
    "psychic",
    "double-team",
    "confuse-ray",
    "swift",
    "dream-eater",
    "rest",
    "slash",
    "substitute",
    "snore",
    "curse",
    "spite",
    "protect",
    "scary-face",
    "mud-slap",
    "destiny-bond",
    "icy-wind",
    "outrage",
    "endure",
    "swagger",
    "fury-cutter",
    "steel-wing",
    "sleep-talk",
    "return",
    "frustration",
    "safeguard",
    "pain-split",
    "dragon-breath",
    "iron-tail",
    "hidden-power",
    "twister",
    "rain-dance",
    "sunny-day",
    "psych-up",
    "ancient-power",
    "shadow-ball",
    "rock-smash",
    "will-o-wisp",
    "facade",
    "secret-power",
    "hyper-voice",
    "air-cutter",
    "silver-wind",
    "aerial-ace",
    "dragon-claw",
    "calm-mind",
    "shock-wave",
    "gravity",
    "natural-gift",
    "payback",
    "heal-block",
    "aura-sphere",
    "dark-pulse",
    "aqua-tail",
    "dragon-pulse",
    "energy-ball",
    "earth-power",
    "giga-impact",
    "shadow-claw",
    "shadow-sneak",
    "rock-climb",
    "defog",
    "draco-meteor",
    "iron-head",
    "stone-edge",
    "charge-beam",
    "ominous-wind",
    "shadow-force",
    "hone-claws",
    "telekinesis",
    "round",
    "echoed-voice",
    "hex",
    "bulldoze",
    "dragon-tail",
    "phantom-force",
    "confide",
    "brutal-swing",
    "breaking-swipe",
    "skitter-smack",
    "poltergeist",
    "dual-wingbeat",
    "tera-blast"
  ],
  "stats": {
    "hp": 150,
    "attack": 100,
    "defense": 120,
    "special-attack": 100,
    "special-defense": 120,
    "speed": 90
  },
  "evolution_chain": [
    "giratina"
  ],
  "flavor_texts": [
    "A Pokémon that is said to live in a world on the reverse side of ours. It appears in an ancient cemetery.",
    "It was banished for its violence. It silently gazed upon the old world from the Distortion World.",
    "This Pokémon is said to live in a world on the reverse side of ours, where common knowledge is distorted and strange.",
    "There is one Hisuian verse that tells of a powerful light creating a deep shadow. I imagine that this deep shadow is Giratina."
  ],
  "text": "Giratina-altered is the Renegade Pokémon. It is a ghost and dragon-type Pokémon. Abilities: pressure, telepathy (hidden). Base stats — HP: 150, Attack: 100, Defense: 120, Sp. Atk: 100, Sp. Def: 120, Speed: 90. Evolution line: giratina. Lore: A Pokémon that is said to live in a world on the reverse side of ours. It appears in an ancient cemetery. It was banished for its violence. It silently gazed upon the old world from the Distortion World. This Pokémon is said to live in a world on the reverse side of ours, where common knowledge is distorted and strange. There is one Hisuian verse that tells of a powerful light creating a deep shadow. I imagine that this deep shadow is Giratina."
}